chemical_calculators/__init__.py
chemical_calculators/core/__init__.py
chemical_calculators/core/atom.py
chemical_calculators/core/composition.py
chemical_calculators/core/consts.py
chemical_calculators/core/quantity.py
chemical_calculators/core/reaction.py
chemical_calculators/core/substance.py
chemical_calculators/core/table.py
chemical_calculators/core/typings.py
chemical_calculators/core/unit.py
chemical_calculators/data/table.json
chemical_calculators/helpers/__init__.py
chemical_calculators/helpers/string.py
chemical_calculators/ui/__init__.py
chemical_calculators/ui/args.py
chemical_calculators/ui/console.py
chemical_calculators/ui/tkinter/__init__.py
chemical_calculators/ui/tkinter/config.py
chemical_calculators/ui/tkinter/main.py
chemical_calculators/ui/tkinter/modules/__init__.py
chemical_calculators/ui/tkinter/modules/reaction.py
chemical_calculators/ui/tkinter/modules/substance.py
chemical_calculators-0.1.0.dist-info/WHEEL
chemical_calculators-0.1.0.dist-info/METADATA
chemical_calculators-0.1.0.dist-info/RECORD
