Metadata-Version: 2.1
Name: chemical-calculators
Version: 0.1.0
Summary: Various calculators for chemistry
Author: Yakovlev Kll
Author-email: yakovlev.kll@gmail.com
Requires-Python: >=3.9,<4.0
Classifier: Programming Language :: Python :: 3
Classifier: Programming Language :: Python :: 3.9
Requires-Dist: numpy (>=1.21.0,<2.0.0)
